JavascriptXuexizhinanCYuyanBianchengWangFix1/README.md
JavascriptXuexizhinanCYuyanBianchengWangFix1/__init__.py
JavascriptXuexizhinanCYuyanBianchengWangFix1/__main__.py
JavascriptXuexizhinanCYuyanBianchengWangFix1/file.epub
JavascriptXuexizhinanCYuyanBianchengWangFix1/index.html
JavascriptXuexizhinanCYuyanBianchengWangFix1/css/__init__.py
JavascriptXuexizhinanCYuyanBianchengWangFix1/css/annotations.css
JavascriptXuexizhinanCYuyanBianchengWangFix1/css/main.css
JavascriptXuexizhinanCYuyanBianchengWangFix1/css/normalize.css
JavascriptXuexizhinanCYuyanBianchengWangFix1/css/popup.css
JavascriptXuexizhinanCYuyanBianchengWangFix1/font/__init__.py
JavascriptXuexizhinanCYuyanBianchengWangFix1/font/fontello.eot
JavascriptXuexizhinanCYuyanBianchengWangFix1/font/fontello.svg
JavascriptXuexizhinanCYuyanBianchengWangFix1/font/fontello.ttf
JavascriptXuexizhinanCYuyanBianchengWangFix1/font/fontello.woff
JavascriptXuexizhinanCYuyanBianchengWangFix1/img/__init__.py
JavascriptXuexizhinanCYuyanBianchengWangFix1/img/annotator-glyph-sprite.png
JavascriptXuexizhinanCYuyanBianchengWangFix1/img/annotator-icon-sprite.png
JavascriptXuexizhinanCYuyanBianchengWangFix1/img/apple-touch-icon.png
JavascriptXuexizhinanCYuyanBianchengWangFix1/img/cancelfullscreen.png
JavascriptXuexizhinanCYuyanBianchengWangFix1/img/close.png
JavascriptXuexizhinanCYuyanBianchengWangFix1/img/fullscreen.png
JavascriptXuexizhinanCYuyanBianchengWangFix1/img/loader.gif
JavascriptXuexizhinanCYuyanBianchengWangFix1/img/menu-icon.png
JavascriptXuexizhinanCYuyanBianchengWangFix1/img/save.png
JavascriptXuexizhinanCYuyanBianchengWangFix1/img/saved.png
JavascriptXuexizhinanCYuyanBianchengWangFix1/img/settings-s.png
JavascriptXuexizhinanCYuyanBianchengWangFix1/img/settings.png
JavascriptXuexizhinanCYuyanBianchengWangFix1/img/star.png
JavascriptXuexizhinanCYuyanBianchengWangFix1/js/__init__.py
JavascriptXuexizhinanCYuyanBianchengWangFix1/js/epub.js
JavascriptXuexizhinanCYuyanBianchengWangFix1/js/epub.min.js
javascript_xuexizhinan_c_yuyan_biancheng_wang_fix1-2025.3.24.0.dist-info/METADATA
javascript_xuexizhinan_c_yuyan_biancheng_wang_fix1-2025.3.24.0.dist-info/WHEEL
javascript_xuexizhinan_c_yuyan_biancheng_wang_fix1-2025.3.24.0.dist-info/entry_points.txt
javascript_xuexizhinan_c_yuyan_biancheng_wang_fix1-2025.3.24.0.dist-info/top_level.txt
javascript_xuexizhinan_c_yuyan_biancheng_wang_fix1-2025.3.24.0.dist-info/RECORD
